MojangAuth/MojangAuth.py
MojangAuth/__init__.py
MojangAuthPython-0.1.4.dist-info/LICENSE
MojangAuthPython-0.1.4.dist-info/METADATA
MojangAuthPython-0.1.4.dist-info/WHEEL
MojangAuthPython-0.1.4.dist-info/top_level.txt
MojangAuthPython-0.1.4.dist-info/RECORD
