Metadata-Version: 2.1
Name: MojangAuthPython
Version: 0.1.4
Summary: MojangAuthPython is a lib for mojang authentification.
Home-page: https://github.com/Asthowen/MojangAuthPython
Author: Asthowen
License: UNKNOWN
Platform: UNKNOWN
Requires-Python: >= 3.6
License-File: LICENSE
Requires-Dist: requests
